pybuildit/__init__.py
pybuildit/calib.py
pybuildit/const.py
pybuildit/lib.py
pybuildit/log.py
pybuildit/path.py
pybuildit/unsafe.py
pybuildit/cli/__init__.py
pybuildit/cli/builditctl.py
pybuildit/gui/__init__.py
pybuildit/gui/builditctl.py
pybuildit/gui/config_tab.py
pybuildit/gui/control_tab.py
pybuildit/gui/graph_tab.py
pybuildit/gui/init_tab.py
pybuildit/gui/log_tab.py
pybuildit/gui/main_panel.py
pybuildit/gui/side_panel.py
pybuildit/gui/top_panel.py
pybuildit/gui/util.py
pybuildit/gui/config/default_params.yml
pybuildit/gui/config/params_sample.yml
pybuildit/gui/config/servo.yml
pybuildit/gui/config/system.yml
pybuildit/gui/config/unsafe-servo.yml
pybuildit/gui/imgs/LED-GREEN.gif
pybuildit/gui/imgs/LED-OFF.gif
pybuildit/gui/imgs/LED-RED.gif
pybuildit-1.0.1.dist-info/METADATA
pybuildit-1.0.1.dist-info/RECORD
pybuildit-1.0.1.dist-info/WHEEL
pybuildit-1.0.1.dist-info/entry_points.txt
pybuildit-1.0.1.dist-info/top_level.txt
